jaanca_utils_encrypt/__init__.py
jaanca_utils_encrypt/utils/__init__.py
jaanca_utils_encrypt/utils/helpers/__init__.py
jaanca_utils_encrypt/utils/helpers/encryption_rsa.py
jaanca_utils_encrypt-0.1.0.dist-info/LICENSE.txt
jaanca_utils_encrypt-0.1.0.dist-info/METADATA
jaanca_utils_encrypt-0.1.0.dist-info/WHEEL
jaanca_utils_encrypt-0.1.0.dist-info/top_level.txt
jaanca_utils_encrypt-0.1.0.dist-info/RECORD
